digitaltwins_on_fhir/__init__.py
digitaltwins_on_fhir/core/__init__.py
digitaltwins_on_fhir/core/base.py
digitaltwins_on_fhir/core/digitaltwins.py
digitaltwins_on_fhir/core/lib.py
digitaltwins_on_fhir/core/loader.py
digitaltwins_on_fhir/core/operator.py
digitaltwins_on_fhir/core/search.py
digitaltwins_on_fhir/core/utils.py
digitaltwins_on_fhir/core/digital_twins/__init__.py
digitaltwins_on_fhir/core/digital_twins/digital_twins.py
digitaltwins_on_fhir/core/digital_twins/knowledgebase.py
digitaltwins_on_fhir/core/digital_twins/measurements.py
digitaltwins_on_fhir/core/digital_twins/process.py
digitaltwins_on_fhir/core/digital_twins/workflow.py
digitaltwins_on_fhir/core/digital_twins/workflow_tool.py
digitaltwins_on_fhir/core/exception/custom_error.py
digitaltwins_on_fhir/core/nzbase/Patient.py
digitaltwins_on_fhir/core/resource/__init__.py
digitaltwins_on_fhir/core/resource/abstract_resource.py
digitaltwins_on_fhir/core/resource/activity_definition.py
digitaltwins_on_fhir/core/resource/appointment.py
digitaltwins_on_fhir/core/resource/composition.py
digitaltwins_on_fhir/core/resource/consent.py
digitaltwins_on_fhir/core/resource/definition.py
digitaltwins_on_fhir/core/resource/diagnostic_report.py
digitaltwins_on_fhir/core/resource/document_reference.py
digitaltwins_on_fhir/core/resource/element.py
digitaltwins_on_fhir/core/resource/encounter.py
digitaltwins_on_fhir/core/resource/endpoint.py
digitaltwins_on_fhir/core/resource/group.py
digitaltwins_on_fhir/core/resource/imaging_study.py
digitaltwins_on_fhir/core/resource/observation.py
digitaltwins_on_fhir/core/resource/patient.py
digitaltwins_on_fhir/core/resource/plan_definition.py
digitaltwins_on_fhir/core/resource/practitioner.py
digitaltwins_on_fhir/core/resource/procedure.py
digitaltwins_on_fhir/core/resource/research_study.py
digitaltwins_on_fhir/core/resource/research_subject.py
digitaltwins_on_fhir/core/resource/task.py
digitaltwins_on_fhir-1.4.0.dist-info/licenses/LICENSE
digitaltwins_on_fhir-1.4.0.dist-info/WHEEL
digitaltwins_on_fhir-1.4.0.dist-info/METADATA
digitaltwins_on_fhir-1.4.0.dist-info/RECORD
